Src/__init__.py
Src/m3d0tr1xnums.py
m3d0tr1xnums/__init__.py
m3d0tr1xnums/m3d0tr1xnums.py
m3d0tr1xnums/map.json
m3d0tr1xnums-0.1.0.dist-info/METADATA
m3d0tr1xnums-0.1.0.dist-info/WHEEL
m3d0tr1xnums-0.1.0.dist-info/top_level.txt
m3d0tr1xnums-0.1.0.dist-info/RECORD
