Metadata-Version: 2.4
Name: m3d0tr1xnums
Version: 0.1.0
Summary: Number encryption/decryption library by M3d0Tr1xLabs
Author: M3d0Tr1xLabs
Classifier: Programming Language :: Python :: 3
Classifier: Operating System :: OS Independent
Requires-Python: >=3.7
Requires-Dist: pytz
Dynamic: author
Dynamic: classifier
Dynamic: requires-dist
Dynamic: requires-python
Dynamic: summary
